database_automation2/__init__.py
database_automation2/mongo_crud.py
databaseautomation2-0.0.6.dist-info/METADATA
databaseautomation2-0.0.6.dist-info/WHEEL
databaseautomation2-0.0.6.dist-info/top_level.txt
databaseautomation2-0.0.6.dist-info/RECORD
